cqu_timetable_new/QTGUI.py
cqu_timetable_new/__init__.py
cqu_timetable_new/__main__.py
cqu_timetable_new/config.txt
cqu_timetable_new/layout/mainWindow.ui
cqu_timetable_new/layout.py
cqu_timetable_new/tkgui.py
readme.md
cqu_timetable_new-0.3.3.2.1.dist-info/entry_points.txt
cqu_timetable_new-0.3.3.2.1.dist-info/LICENSE
cqu_timetable_new-0.3.3.2.1.dist-info/WHEEL
cqu_timetable_new-0.3.3.2.1.dist-info/METADATA
cqu_timetable_new-0.3.3.2.1.dist-info/RECORD
