Metadata-Version: 2.1
Name: cqu-timetable-new
Version: 0.3.3.2.1
Summary: Generate CQU timetable iCalendar (ics) file
Home-page: https://github.com/weearc/cqu_timetable_new
License: AGPL-3.0-only
Keywords: ics,cqu,icalendar,timetable
Author: weearc
Author-email: qby19981121@gmail.com
Requires-Python: >=3.8,<3.11
Classifier: License :: OSI Approved :: GNU Affero General Public License v3
Classifier: Programming Language :: Python :: 3
Classifier: Programming Language :: Python :: 3.10
Classifier: Programming Language :: Python :: 3.8
Classifier: Programming Language :: Python :: 3.9
Provides-Extra: pyqt
Provides-Extra: tk
Requires-Dist: easygui (>=0.98.2,<0.99.0); extra == "tk"
Requires-Dist: icalendar (>=4.0.7,<5.0.0)
Requires-Dist: openpyxl (>=3.0.6,<4.0.0)
Requires-Dist: pyside2 (==5.15.2); extra == "pyqt"
Project-URL: Bug Tracker, https://github.com/weearc/cqu_timetable_new/issues
Project-URL: Repository, https://github.com/weearc/cqu_timetable_new
